Metadata-Version: 2.1
Name: pysflow
Version: 0.1.2
Summary: sFlow parser, written in Python
Home-page: https://github.com/reening/pysflow
Author: Martijn Reening
Author-email: martijn@reening.net
License: BSD 3-clause "New" or "Revised License"
Platform: UNKNOWN
Classifier: Development Status :: 1 - Planning
Classifier: Intended Audience :: Developers
Classifier: License :: OSI Approved :: BSD License
Classifier: Operating System :: OS Independent
Classifier: Programming Language :: Python :: 3
Classifier: Topic :: System :: Networking :: Monitoring
